dspftwplot/__init__.py
dspftwplot/constellation_plot.py
dspftwplot/exceptions.py
dspftwplot/plot_3d_complex.py
dspftwplot/plot_complex.py
dspftwplot/plot_func_slider.py
dspftwplot/plot_slider.py
dspftwplot-2024.243.75.dist-info/LICENSE
dspftwplot-2024.243.75.dist-info/METADATA
dspftwplot-2024.243.75.dist-info/WHEEL
dspftwplot-2024.243.75.dist-info/RECORD
